kicad_pycbnew-0.1.1.post1.dist-info/licenses/LICENSE
pycbnew/__init__.py
pycbnew/composites/__init__.py
pycbnew/composites/abstract_path.py
pycbnew/composites/gr_line_path.py
pycbnew/composites/segment_path.py
pycbnew/primitives/__init__.py
pycbnew/primitives/footprint.py
pycbnew/primitives/gr_elements.py
pycbnew/primitives/kicad.py
pycbnew/primitives/layer.py
pycbnew/primitives/net.py
pycbnew/primitives/project.py
pycbnew/primitives/segment.py
pycbnew/primitives/sexpressions.py
pycbnew/primitives/via.py
pycbnew/primitives/zone.py
pycbnew/utils/__init__.py
pycbnew/utils/bernstein.py
pycbnew/utils/geometry.py
kicad_pycbnew-0.1.1.post1.dist-info/METADATA
kicad_pycbnew-0.1.1.post1.dist-info/WHEEL
kicad_pycbnew-0.1.1.post1.dist-info/top_level.txt
kicad_pycbnew-0.1.1.post1.dist-info/RECORD
