Metadata-Version: 2.4
Name: kicad-pycbnew
Version: 0.1.1.post1
Summary: kicad-pycbnew is a Python module for creating printed circuit boards designs compatible with KiCad's pcbnew,
Author: Vincent Raspal
License: MIT
Project-URL: Homepage, https://gitlab.com/vinraspa/kicad-pycbnew
Project-URL: Repository, https://gitlab.com/vinraspa/kicad-pycbnew
Project-URL: Issues, https://gitlab.com/vinraspa/kicad-pycbnew/issues
Project-URL: Examples, https://gitlab.com/vinraspa/kicad-pycbnew/-/tree/v0.1.1/examples
Keywords: kicad,pcb,pcbnew,hardware,automation
Classifier: Programming Language :: Python :: 3
Classifier: License :: OSI Approved :: MIT License
Classifier: Operating System :: OS Independent
Classifier: Topic :: Scientific/Engineering :: Electronic Design Automation (EDA)
Requires-Python: >=3.10
License-File: LICENSE
Requires-Dist: StrEnum>=0.4
Requires-Dist: pyparsing<4.0,>=3.0
Dynamic: license-file
